{
    "1": "poisson_noise",
    "2": "gaussian_noise",
    "3": "impulse_noise",
    "4": "defocus_blur",
    "5": "glass_blur",
    "6": "motion_blur",
    "7": "increase_brightness",
    "8": "contrast",
    "9": "elastic",
    "10": "pixelate",
    "11": "jpeg_filter",
    "12": "translate_image",
    "13": "scale_image",
    "14": "fog_mapping",
    "15": "splatter_mapping",
    "16": "dotted_lines_mapping",
    "17": "zigzag_mapping",
    "18": "canny_edges_mapping",
    "19": "speckle_noise_filter",
    "20": "false_color_filter",
    "21": "low_pass_filter",
    "22": "phase_scrambling",
    "23": "histogram_equalisation",
    "24": "white_balance_filter",
    "25": "sharpen_filter",
    "26": "grayscale_filter",
    "27": "fog_filter",
    "28": "frost_filter",
    "29": "snow_filter",
    "30": "dynamic_snow_filter",
    "31": "dynamic_rain_filter",
    "32": "object_overlay",
    "33": "dynamic_object_overlay",
    "34": "dynamic_sun_filter",
    "35": "dynamic_lightning_filter",
    "36": "dynamic_smoke_filter",
    "37": "perturb_high_attention_regions",
    "38": "posterize_filter",
    "39": "cutout_filter",
    "40": "sample_pairing_filter",
    "41": "gaussian_blur",
    "42": "saturation_filter",
    "43": "saturation_decrease_filter",
    "44": "candy",
    "45": "la_muse",
    "46": "mosaic",
    "47": "feathers",
    "48": "the_scream",
    "49": "udnie",
    "50": "sim2real"
}